[
  {
    "line": 1,
    "elements": [
      {
        "line": 3,
        "name": "",
        "description": "",
        "type": "background",
        "keyword": "Background",
        "steps": [
          {
            "result": {
              "duration": 1755573700,
              "status": "passed"
            },
            "line": 4,
            "name": "the user must be in chrome browser",
            "match": {
              "location": "StepDefinitionFile.StepDef.setup()"
            },
            "keyword": "Given "
          }
        ]
      },
      {
        "start_timestamp": "2026-01-28T11:39:40.496Z",
        "line": 7,
        "name": "Validate signup using Excel data",
        "description": "",
        "id": "to-perform-signup;validate-signup-using-excel-data",
        "type": "scenario",
        "keyword": "Scenario",
        "steps": [
          {
            "result": {
              "duration": 3860093800,
              "status": "passed"
            },
            "line": 8,
            "name": "The user in the signup page",
            "match": {
              "location": "StepDefinitionFile.StepDef.signup_page()"
            },
            "keyword": "Given "
          },
          {
            "result": {
              "duration": 2679660000,
              "status": "passed"
            },
            "line": 9,
            "name": "The user enters signup details from excel",
            "match": {
              "location": "StepDefinitionFile.StepDef.enterSignupDetailsFromExcel()"
            },
            "keyword": "When "
          },
          {
            "result": {
              "duration": 45012675100,
              "status": "passed"
            },
            "line": 10,
            "name": "The user click on i am not a robot",
            "match": {
              "location": "StepDefinitionFile.StepDef.clickRobot()"
            },
            "keyword": "And "
          },
          {
            "result": {
              "duration": 4307252800,
              "status": "passed"
            },
            "line": 11,
            "name": "The user click on continue",
            "match": {
              "location": "StepDefinitionFile.StepDef.clickContinue()"
            },
            "keyword": "And "
          },
          {
            "result": {
              "duration": 999100,
              "status": "passed"
            },
            "line": 12,
            "name": "the user will enter in the website",
            "match": {
              "location": "StepDefinitionFile.StepDef.enterWebsite()"
            },
            "keyword": "Then "
          }
        ],
        "tags": [
          {
            "name": "@tag1"
          }
        ]
      }
    ],
    "name": "To perform SignUp",
    "description": "",
    "id": "to-perform-signup",
    "keyword": "Feature",
    "uri": "file:src/test/java/FeatureFile/LoginValidate.feature",
    "tags": []
  }
]